setup.cfg
setup.py
./bkapi/__init__.py
./bkapi/bk_apigateway/__init__.py
./bkapi/bk_apigateway/client.py
./bkapi/bk_apigateway/client.pyi
./bkapi/bk_apigateway/shortcuts.py
./bkapigw/__init__.py
./bkapigw/__init__.pyi
./bkapigw/bk_apigateway/__init__.py
./bkapigw/bk_apigateway/__init__.pyi
./bkapigw/bk_apigateway/base.py
./bkapigw/bk_apigateway/client.py
./bkapigw/bk_apigateway/conf.py
./bkapigw/bk_apigateway/exceptions.py
./bkapigw/bk_apigateway/resources.py
./bkapigw/bk_apigateway/shortcuts.py
./bkapigw/bk_apigateway/utils.py
bkapi_bk_apigateway.egg-info/PKG-INFO
bkapi_bk_apigateway.egg-info/SOURCES.txt
bkapi_bk_apigateway.egg-info/dependency_links.txt
bkapi_bk_apigateway.egg-info/namespace_packages.txt
bkapi_bk_apigateway.egg-info/requires.txt
bkapi_bk_apigateway.egg-info/top_level.txt