Metadata-Version: 2.1
Name: bkapi-bk-apigateway
Version: 1.0.12
Summary: 蓝鲸API网关
Author: blueking
License: Apach License 2.0
Requires-Python: !=3.0.*,!=3.1.*,!=3.2.*,!=3.3.*,!=3.4.*,!=3.5.*,<4.0,>=2.7
Requires-Dist: bkapi-client-core<2.0.0,>=1.0.2
Provides-Extra: django
Requires-Dist: bkapi-client-core[django]<2.0.0,>=1.0.2; extra == "django"
